agentwallet/__init__.py
agentwallet/account.py
agentwallet/agent.py
agentwallet/api_client.py
agentwallet/exceptions.py
agentwallet/transaction.py
agentwallet/wallet.py
agent_wallet_sdk-0.0.1.dist-info/LICENSE
agent_wallet_sdk-0.0.1.dist-info/METADATA
agent_wallet_sdk-0.0.1.dist-info/WHEEL
agent_wallet_sdk-0.0.1.dist-info/top_level.txt
agent_wallet_sdk-0.0.1.dist-info/RECORD
